wexample_filestate_php-0.0.14.dist-info/METADATA
wexample_filestate_php-0.0.14.dist-info/WHEEL
wexample_filestate_php-0.0.14.dist-info/entry_points.txt
wexample_filestate_php/__init__.py
wexample_filestate_php/config_option/__init__.py
wexample_filestate_php/config_option/phpcs_fixer_config_option.py
wexample_filestate_php/config_value/__init__.py
wexample_filestate_php/config_value/php_config_value.py
wexample_filestate_php/const/__init__.py
wexample_filestate_php/const/php_file.py
wexample_filestate_php/file/__init__.py
wexample_filestate_php/file/php_file.py
wexample_filestate_php/option/__init__.py
wexample_filestate_php/option/php/__init__.py
wexample_filestate_php/option/php/abstract_php_file_content_option.py
wexample_filestate_php/option/php/phpcs_fixer_option.py
wexample_filestate_php/option/php_option.py
wexample_filestate_php/options_provider/__init__.py
wexample_filestate_php/options_provider/php_options_provider.py
wexample_filestate_php/py.typed
wexample_filestate_php/resources/__init__.py
wexample_filestate_php/resources/docker/.php-cs-fixer.dist.php
wexample_filestate_php/resources/docker/Dockerfile.php-option
wexample_filestate_php/resources/docker/__init__.py
wexample_filestate_php-0.0.14.dist-info/RECORD
